Workbook

Sheet Portada
B8: Modelo de ahorros operativos del sector transportador
B9: Objetivo específico 6 · Actividad 4 — Ahorro por cruce y proyección anual 2026 y 2030 (tractocamiones)
B11: Objetivo | C11: OE 6: Determinar la eficiencia logística del sistema intermodal Ferropista, calculando la reducción de tiempos de ciclo y de costos operativos frente a la operación actual por la Ruta 40.
B12: Actividad | C12: 4. Proyección de los ahorros operativos anuales para el sector transportador
B13: Entregable / formato | C13: Modelo de ahorros operativos · Documento Excel
B14: Periodo | C14: Bloque 2 del Plan de Acción (5 oct - 7 nov 2026)
B15: Responsable asignado | C15: Torrente Parra Daniel Ignacio
B16: Apoyo en la ejecución | C16: Tamayo Osorio Miguel Ángel, con apoyo de IA (Claude)
B17: Semillero | C17: Semillero de Investigación GEOPAV · Ingeniería Civil · Universidad de Ibagué · Paz y Región 2026B
B18: Fecha de elaboración | C18: 29 sep 2026
B19: Advertencia | C19: La fuente no publica la tarifa de la Ferropista: el ahorro bruto es un techo que se reparte entre operador y transportador. Solo tractocamiones con costos eficientes SICE-TAC; pesos constantes de sep 2026; demanda del proponente (INVÍAS 2017 proyectado).
B21: Índice de hojas (tabla de contenido)
B22: Entradas | C22: Tabla 1. Entradas leídas de las Act 1-3 y de la fuente primaria
B23: Por viaje | C23: Tabla 2. Costo de un cruce por carretera y por Ferropista (sin tarifa) y tarifa de indiferencia
B24: Anual | C24: Tabla 3. Demanda captada · Tabla 4. Ahorro bruto y horas ahorradas por año
B25: Tarifa | C25: Tabla 5. Ahorro que le queda al transportador según la tarifa
B26: Contraste | C26: Tabla 6. Contraste con las cifras de la fuente
B27: Fuentes | C27: Tabla 7. Fuentes citadas y huella md5
B29: Índice de tablas: tablas 1 a 7 según el índice de hojas. Índice de figuras: no tiene (las figuras van en el informe de la Act 5). Índice de anexos: no tiene. Script: OE6_Logistica/Act4_Ahorros/modelo_ahorros_OE6.py. Convención: azul = entrada leída de una fuente; verde = valor leído de otro producto del OE 6; fondo amarillo = hipótesis [H]; negro = fórmula. Marcas: [F] fuente citada · [CP] cálculo propio reproducible · [H] hipótesis declarada · [DA] dato por consultar. Elaborado con apoyo de IA (Claude) y verificado contra las fuentes.

Sheet Entradas
A1: Tabla 1. Entradas del modelo
A3: Entrada | B3: Valor | C3: Unidad | D3: Origen | E3: Marca
A4: Costo fijo por hora de vehículo | B4: 74054.477 | C4: $/h | D4: Act 3 · matriz_costos_unitarios_OE6.json | E4: [CP]
A5: Costo variable por km sin combustible | B5: 1716.2912 | C5: $/km | D5: Act 3 | E5: [CP]
A6: Factor de otros costos f | B6: 0.224824 | C6: — | D6: Act 3 | E6: [CP]
A7: Combustible por km · plano | B7: 1792.5926 | C7: $/km | D7: Act 3 | E7: [CP]
A8: Combustible por km · ondulado | B8: 2420 | C8: $/km | D8: Act 3 | E8: [CP]
A9: Combustible por km · montaña | B9: 3563.1902 | C9: $/km | D9: Act 3 | E9: [CP]
A10: Combustible por km · urbano | B10: 3563.1902 | C10: $/km | D10: Act 3 | E10: [CP]
A11: Combustible por km · afirmado | B11: 5611.5942 | C11: $/km | D11: Act 3 | E11: [CP]
A12: Grandes camiones en el Alto de La Línea (2017) | B12: 2100 | C12: veh/día | D12: INVÍAS 2017 citado por la fuente | E12: [F, dia. 10]
A13: Camiones medianos (2017) | B13: 1700 | C13: veh/día | D13: INVÍAS 2017 citado por la fuente | E13: [F, dia. 10]
A14: Crecimiento anual | B14: 0.03 | C14: — | D14: Fuente primaria | E14: [F, dia. 10]
A15: Captación de grandes camiones en 2030 | B15: 0.9 | C15: — | D15: Fuente primaria | E15: [F, dia. 10]
... A18: Capacidad Ferropista (camiones/día) | B18: 4900 | C18: camiones/día | D18: Act 2 (140 trenes × 35) | E18: [F→CP]
A20: Por sentido y escenario (Act 1 y Act 2) | B20: Ibagué → Calarcá | C20: Calarcá → Ibagué | D20: Unidad | E20: Marca
A21: Horas por carretera · Mínimo | B21: 2.9975816 | C21: 2.4734654 | D21: h | E21: Act 1 / Act 2 / Act 3
A22: Horas por carretera · Típico | B22: 4 | C22: 4 | D22: h | E22: Act 1 / Act 2 / Act 3
A23: Horas por carretera · Máximo | B23: 5 | C23: 5 | D23: h | E23: Act 1 / Act 2 / Act 3
A24: Horas por Ferropista · Mínimo | B24: 1.8127427 | C24: 1.8120908 | D24: h | E24: Act 1 / Act 2 / Act 3
A25: Horas por Ferropista · Típico | B25: 2.24622 | C25: 2.2453036 | D25: h | E25: Act 1 / Act 2 / Act 3
A26: Horas por Ferropista · Máximo | B26: 2.9364905 | C26: 2.9350505 | D26: h | E26: Act 1 / Act 2 / Act 3
A27: Km por carretera | B27: 85.01 | C27: 76.17 | D27: km | E27: Act 1 / Act 2 / Act 3
A28: Combustible del cruce por carretera (sin f) | B28: 253917.54 | C28: 213890.13 | D28: $ | E28: Act 1 / Act 2 / Act 3
A29: Peajes del cruce por carretera | B29: 106700 | C29: 42900 | D29: $ | E29: Act 1 / Act 2 / Act 3
A30: Km de acceso con Ferropista | B30: 21.4045 | C30: 21.3829 | D30: km | E30: Act 1 / Act 2 / Act 3

Sheet Por viaje
A1: Tabla 2. Costo de un cruce Ibagué–Calarcá por carretera y por Ferropista (sin tarifa) y tarifa de indiferencia
A3: Sentido | B3: Rango | C3: Horas carretera | D3: Horas Ferropista | E3: Horas ahorradas | F3: Costo carretera ($) | G3: Costo Ferropista sin tarifa ($) | H3: Tarifa de indiferencia ($/camión) | I3: Reducción del costo (%)
A4: Ibagué → Calarcá | B4: Bajo | C4: =Entradas!B21 -> 2.9975816 | D4: =Entradas!B26 -> 2.9364905 | E4: =C4-D4 -> 0.061091078 | F4: =(Entradas!$B$4*C4+Entradas!B28+Entradas!B27*Entradas!$B$5+Entradas!B29)*(1+Entradas!$B$6) -> 892288.94 | G4: =(Entradas!$B$4*D4+Entradas!B30*(Entradas!$B$5+Entradas!$B$11))*(1+Entradas!$B$6) -> 458463.86 | H4: =F4-G4 -> 433825.08 | I4: =H4/F4 -> 0.48619349
A5: Ibagué → Calarcá | B5: Central | C5: =Entradas!B22 -> 4 | D5: =Entradas!B25 -> 2.24622 | E5: =C5-D5 -> 1.75378 | F5: =(Entradas!$B$4*C5+Entradas!B28+Entradas!B27*Entradas!$B$5+Entradas!B29)*(1+Entradas!$B$6) -> 983212 | G5: =(Entradas!$B$4*D5+Entradas!B30*(Entradas!$B$5+Entradas!$B$9))*(1+Entradas!$B$6) -> 342151.29 | H5: =F5-G5 -> 641060.72 | I5: =H5/F5 -> 0.6520066
A6: Ibagué → Calarcá | B6: Alto | C6: =Entradas!B23 -> 5 | D6: =Entradas!B24 -> 1.8127427 | E6: =C6-D6 -> 3.1872573 | F6: =(Entradas!$B$4*C6+Entradas!B28+Entradas!B27*Entradas!$B$5+Entradas!B29)*(1+Entradas!$B$6) -> 1073915.7 | G6: =(Entradas!$B$4*D6+Entradas!B30*(Entradas!$B$5+Entradas!$B$8))*(1+Entradas!$B$6) -> 272862.57 | H6: =F6-G6 -> 801053.13 | I6: =H6/F6 -> 0.74591807
A8: Calarcá → Ibagué | B8: Bajo | C8: =Entradas!C21 -> 2.4734654 | D8: =Entradas!C26 -> 2.9350505 | E8: =C8-D8 -> -0.46158505 | F8: =(Entradas!$B$4*C8+Entradas!C28+Entradas!C27*Entradas!$B$5+Entradas!C29)*(1+Entradas!$B$6) -> 698996.31 | G8: =(Entradas!$B$4*D8+Entradas!C30*(Entradas!$B$5+Entradas!$B$11))*(1+Entradas!$B$6) -> 458139.38 | H8: =F8-G8 -> 240856.93 | I8: =H8/F8 -> 0.34457539
A9: Calarcá → Ibagué | B9: Central | C9: =Entradas!C22 -> 4 | D9: =Entradas!C25 -> 2.2453036 | E9: =C9-D9 -> 1.7546964 | F9: =(Entradas!$B$4*C9+Entradas!C28+Entradas!C27*Entradas!$B$5+Entradas!C29)*(1+Entradas!$B$6) -> 837458.64 | G9: =(Entradas!$B$4*D9+Entradas!C30*(Entradas!$B$5+Entradas!$B$9))*(1+Entradas!$B$6) -> 341928.49 | H9: =F9-G9 -> 495530.15 | I9: =H9/F9 -> 0.59170702
A10: Calarcá → Ibagué | B10: Alto | C10: =Entradas!C23 -> 5 | D10: =Entradas!C24 -> 1.8120908 | E10: =C10-D10 -> 3.1879092 | F10: =(Entradas!$B$4*C10+Entradas!C28+Entradas!C27*Entradas!$B$5+Entradas!C29)*(1+Entradas!$B$6) -> 928162.35 | G10: =(Entradas!$B$4*D10+Entradas!C30*(Entradas!$B$5+Entradas!$B$8))*(1+Entradas!$B$6) -> 272694 | H10: =F10-G10 -> 655468.34 | I10: =H10/F10 -> 0.7062001
A12: Rango bajo = carretera en flujo libre (modelo SICE-TAC) frente a la Ferropista más lenta; central = típico frente a típico; alto = carretera con pare y siga frente a la Ferropista más rápida. Una tarifa de indiferencia negativa significa que, en ese caso, la carretera es más barata aunque la Ferropista no cobre nada. No incluye cargue ni descargue de la mercancía (iguales en los dos modos).

Sheet Anual
A1: Tabla 3. Demanda captada por la Ferropista (tractocamiones)
A3: Año | B3: Grandes camiones/día (proyección) | C3: Captación | D3: Camiones/día captados | E3: Camiones/año | F3: Ocupación de la capacidad
A4: 2026 | B4: =Entradas!$B$12*(1+Entradas!$B$14)^(A4-2017) -> 2740.0237 | C4: =Entradas!$B$15 -> 0.9 | D4: =B4*C4 -> 2466.0213 | E4: =D4*365 -> 900097.78 | F4: =D4/Entradas!$B$18 -> 0.50326966
A5: 2030 | B5: =Entradas!$B$12*(1+Entradas!$B$14)^(A5-2017) -> 3083.9208 | C5: =Entradas!$B$15 -> 0.9 | D5: =B5*C5 -> 2775.5287 | E5: =D5*365 -> 1013068 | F5: =D5/Entradas!$B$18 -> 0.56643443
A7: La captación del 90 % es la prevista por la fuente para 2030; se aplica igual a 2026 para mostrar el orden de magnitud con la demanda de hoy [H].
A9: Tabla 4. Ahorro operativo bruto anual y horas ahorradas
A10: Año | B10: Rango | C10: Ahorro bruto ($/año) | D10: Ahorro bruto (miles de millones $) | E10: Horas ahorradas, grandes camiones | F10: Horas ahorradas, medianos [H] | G10: Horas totales (millones)
A11: 2026 | B11: Bajo | C11: =Entradas!$B$17*$E$4*('Por viaje'!H4+'Por viaje'!H8) -> 3.0363989e+11 | D11: =C11/1000000000 -> 303.63989 | E11: =Entradas!$B$17*$E$4*('Por viaje'!E4+'Por viaje'!E8) -> -180241.87 | F11: =Entradas!$B$17*Entradas!$B$13*(1+Entradas!$B$14)^(A11-2017)*Entradas!$B$16*365*('Por viaje'!E4+'Por viaje'!E8) -> -97273.388 | G11: =(E11+F11)/1000000 -> -0.27751525
A12: 2026 | B12: Central | C12: =Entradas!$B$17*$E$4*('Por viaje'!H5+'Por viaje'!H9) -> 5.1152146e+11 | D12: =C12/1000000000 -> 511.52146 | E12: =Entradas!$B$17*$E$4*('Por viaje'!E5+'Por viaje'!E9) -> 1578985.9 | F12: =Entradas!$B$17*Entradas!$B$13*(1+Entradas!$B$14)^(A12-2017)*Entradas!$B$16*365*('Por viaje'!E5+'Por viaje'!E9) -> 852151.14 | G12: =(E12+F12)/1000000 -> 2.4311371
A13: 2026 | B13: Alto | C13: =Entradas!$B$17*$E$4*('Por viaje'!H6+'Por viaje'!H10) -> 6.5550587e+11 | D13: =C13/1000000000 -> 655.50587 | E13: =Entradas!$B$17*$E$4*('Por viaje'!E6+'Por viaje'!E10) -> 2869136.6 | F13: =Entradas!$B$17*Entradas!$B$13*(1+Entradas!$B$14)^(A13-2017)*Entradas!$B$16*365*('Por viaje'!E6+'Por viaje'!E10) -> 1548422.9 | G13: =(E13+F13)/1000000 -> 4.4175596
A14: 2030 | B14: Bajo | C14: =Entradas!$B$17*$E$5*('Por viaje'!H4+'Por viaje'!H8) -> 3.4174937e+11 | D14: =C14/1000000000 -> 341.74937 | E14: =Entradas!$B$17*$E$5*('Por viaje'!E4+'Por viaje'!E8) -> -202863.81 | F14: =Entradas!$B$17*Entradas!$B$13*(1+Entradas!$B$14)^(A14-2017)*Entradas!$B$16*365*('Por viaje'!E4+'Por viaje'!E8) -> -109482.06 | G14: =(E14+F14)/1000000 -> -0.31234586
A15: 2030 | B15: Central | C15: =Entradas!$B$17*$E$5*('Por viaje'!H5+'Por viaje'!H9) -> 5.7572191e+11 | D15: =C15/1000000000 -> 575.72191 | E15: =Entradas!$B$17*$E$5*('Por viaje'!E5+'Por viaje'!E9) -> 1777162.6 | F15: =Entradas!$B$17*Entradas!$B$13*(1+Entradas!$B$14)^(A15-2017)*Entradas!$B$16*365*('Por viaje'!E5+'Por viaje'!E9) -> 959103.62 | G15: =(E15+F15)/1000000 -> 2.7362662
A16: 2030 | B16: Alto | C16: =Entradas!$B$17*$E$5*('Por viaje'!H6+'Por viaje'!H10) -> 7.3777764e+11 | D16: =C16/1000000000 -> 737.77764 | E16: =Entradas!$B$17*$E$5*('Por viaje'!E6+'Por viaje'!E10) -> 3229238.5 | F16: =Entradas!$B$17*Entradas!$B$13*(1+Entradas!$B$14)^(A16-2017)*Entradas!$B$16*365*('Por viaje'!E6+'Por viaje'!E10) -> 1742763.7 | G16: =(E16+F16)/1000000 -> 4.9720022
A18: Horas de camiones medianos [H]: se les aplica la misma reducción de tiempo que a los tractocamiones solo para comparar con la cifra de horas de la fuente; su ahorro en pesos no se calcula porque el SICE-TAC se consultó solo para 3S3.

Sheet Tarifa
A1: Tabla 5. Ahorro anual que le queda al transportador según la tarifa (miles de millones de $, año 2030)
A3: Tarifa como fracción de la tarifa de indiferencia | B3: Bajo | C3: Central | D3: Alto
A4: 0 | B4: =Anual!D14*(1-$A4) -> 341.74937 | C4: =Anual!D15*(1-$A4) -> 575.72191 | D4: =Anual!D16*(1-$A4) -> 737.77764
A5: 0.5 | B5: =Anual!D14*(1-$A5) -> 170.87468 | C5: =Anual!D15*(1-$A5) -> 287.86096 | D5: =Anual!D16*(1-$A5) -> 368.88882
A6: 0.75 | B6: =Anual!D14*(1-$A6) -> 85.437342 | C6: =Anual!D15*(1-$A6) -> 143.93048 | D6: =Anual!D16*(1-$A6) -> 184.44441
A7: 1 | B7: =Anual!D14*(1-$A7) -> 0 | C7: =Anual!D15*(1-$A7) -> 0 | D7: =Anual!D16*(1-$A7) -> 0
A9: Con tarifa = 100 % de la de indiferencia, todo el ahorro lo captura el operador y el transportador queda igual que por carretera. La fuente no dice cómo se reparte.

Sheet Contraste
A1: Tabla 6. Contraste con las cifras de la fuente (año 2030)
A3: Indicador | B3: Fuente | C3: Este modelo · bajo | D3: Este modelo · central | E3: Este modelo · alto | F3: Marca de la fuente
A4: Horas ahorradas al año (millones) | B4: 5 | C4: =Anual!G14 -> -0.31234586 | D4: =Anual!G15 -> 2.7362662 | E4: =Anual!G16 -> 4.9720022 | F4: [F, dia. 28]; la dia. 29 rotula 5,3
A5: Ahorro del sector transporte (billones de $) | B5: 2.5 | C5: =Anual!D14/1000 -> 0.34174937 | D5: =Anual!D15/1000 -> 0.57572191 | E5: =Anual!D16/1000 -> 0.73777764 | F5: [F, dia. 28]
A6: Tiempo de cruce: actual → Ferropista | B6: 4 h → 70 min | C6: ver Act 2 | D6: 4,00 h → 135 min (Ibagué → Calarcá) | F6: [F, dia. 29]
A8: La fuente no explica cómo obtiene 5,0 M h ni 2,5 billones (qué vehículos, qué valor del tiempo, qué año de precios). Este modelo cuenta solo costos de operación de tractocamiones con precios de sep 2026; no incluye el valor del tiempo de la carga, ni de los pasajeros, ni externalidades. Por eso la diferencia no prueba que la fuente esté mal: muestra cuánto de su cifra no se puede reproducir con datos oficiales de costo de operación.

Sheet Fuentes
A1: Tabla 7. Fuentes citadas y huella md5 de los archivos usados
A3: Clave | B3: Referencia | C3: Archivo local | D3: md5
A4: PON | B4: Fernández Ordóñez, H. O. (2025). Túnel para cruce férreo de la Cordillera Central de los Andes y semilla para la Estrella Andina. XX Seminario Andino de Túneles y Obras Subterráneas, SAI, Medellín, 8 oct 2025. Fuente primaria del proyecto. | C4: Túnel para cruce férreo cordillera Central -SAI- 08octubre2025.pdf | D4: 2e7d264eb6d98f368dc9a6bd5bf5bd6d
A5: SICETAC_IBG_CAL | B5: Ministerio de Transporte. SICE-TAC, consulta pública (plc.mintransporte.gov.co), periodo de referencia 20260901: tractocamión 3S3, portacontenedores, contenedor cargado, cargado, 2 h de cargue y 2 h de descargue. Rutas 14037 (Ibagué–Calarcá) y 15393 (Calarcá–Ibagué). Consultado y guardado en PDF el 29 sep 2026. | C5: OE6_Logistica/Fuentes/sicetac_IBG_CAL_3S3.pdf | D5: c991f42266763925dbb7f1ff4d959ed5
A6: SICETAC_CAL_IBG | B6: Ministerio de Transporte. SICE-TAC, consulta pública (plc.mintransporte.gov.co), periodo de referencia 20260901: tractocamión 3S3, portacontenedores, contenedor cargado, cargado, 2 h de cargue y 2 h de descargue. Rutas 14037 (Ibagué–Calarcá) y 15393 (Calarcá–Ibagué). Consultado y guardado en PDF el 29 sep 2026. | C6: OE6_Logistica/Fuentes/sicetac_CAL_IBG_3S3.pdf | D6: d5db8d1a5738d305169b755f79936152
